{"\u03b31":{"climate change":0,"ecotoxicity: freshwater":0,"energy resources: non-renewable":0,"acidification":0,"material resources: metals\/minerals":0,"human toxicity: non-carcinogenic":0,"human toxicity: carcinogenic":0},"\u03b32":{"climate change":0,"ecotoxicity: freshwater":0,"energy resources: non-renewable":0,"acidification":0,"material resources: metals\/minerals":0,"human toxicity: non-carcinogenic":0,"human toxicity: carcinogenic":0},"\u03b33":{"climate change":0,"ecotoxicity: freshwater":0,"energy resources: non-renewable":0,"acidification":0,"material resources: metals\/minerals":0,"human toxicity: non-carcinogenic":0,"human toxicity: carcinogenic":0},"\u03b34":{"climate change":0,"ecotoxicity: freshwater":0,"energy resources: non-renewable":0,"acidification":0,"material resources: metals\/minerals":0,"human toxicity: non-carcinogenic":0,"human toxicity: carcinogenic":0},"\u03b35":{"climate change":0,"ecotoxicity: freshwater":0,"energy resources: non-renewable":0,"acidification":0,"material resources: metals\/minerals":0,"human toxicity: non-carcinogenic":0,"human toxicity: carcinogenic":0},"\u03b36":{"climate change":0,"ecotoxicity: freshwater":0,"energy resources: non-renewable":0,"acidification":0,"material resources: metals\/minerals":0,"human toxicity: non-carcinogenic":0,"human toxicity: carcinogenic":0},"\u03b37":{"climate change":0,"ecotoxicity: freshwater":0,"energy resources: non-renewable":0,"acidification":0,"material resources: metals\/minerals":0,"human toxicity: non-carcinogenic":0,"human toxicity: carcinogenic":0},"\u03b38":{"climate change":0,"ecotoxicity: freshwater":0,"energy resources: non-renewable":0,"acidification":0,"material resources: metals\/minerals":0,"human toxicity: non-carcinogenic":0,"human toxicity: carcinogenic":0},"\u03b39":{"climate change":0,"ecotoxicity: freshwater":0,"energy resources: non-renewable":0,"acidification":0,"material resources: metals\/minerals":0,"human toxicity: non-carcinogenic":0,"human toxicity: carcinogenic":0},"\u03b310":{"climate change":0,"ecotoxicity: freshwater":0,"energy resources: non-renewable":0,"acidification":0,"material resources: metals\/minerals":0,"human toxicity: non-carcinogenic":0,"human toxicity: carcinogenic":0},"\u03b311":{"climate change":0,"ecotoxicity: freshwater":0,"energy resources: non-renewable":0,"acidification":0,"material resources: metals\/minerals":0,"human toxicity: non-carcinogenic":0,"human toxicity: carcinogenic":0},"\u03b312":{"climate change":0,"ecotoxicity: freshwater":0,"energy resources: non-renewable":0,"acidification":0,"material resources: metals\/minerals":0,"human toxicity: non-carcinogenic":0,"human toxicity: carcinogenic":0},"\u03b313":{"climate change":0,"ecotoxicity: freshwater":0,"energy resources: non-renewable":0,"acidification":0,"material resources: metals\/minerals":0,"human toxicity: non-carcinogenic":0,"human toxicity: carcinogenic":0},"\u03b314":{"climate change":0,"ecotoxicity: freshwater":0,"energy resources: non-renewable":0,"acidification":0,"material resources: metals\/minerals":0,"human toxicity: non-carcinogenic":0,"human toxicity: carcinogenic":0},"\u03b315":{"climate change":0,"ecotoxicity: freshwater":0,"energy resources: non-renewable":0,"acidification":0,"material resources: metals\/minerals":0,"human toxicity: non-carcinogenic":0,"human toxicity: carcinogenic":0},"\u03b316":{"climate change":0,"ecotoxicity: freshwater":0,"energy resources: non-renewable":0,"acidification":0,"material resources: metals\/minerals":0,"human toxicity: non-carcinogenic":0,"human toxicity: carcinogenic":0},"\u03b317":{"climate change":0,"ecotoxicity: freshwater":0,"energy resources: non-renewable":0,"acidification":0,"material resources: metals\/minerals":0,"human toxicity: non-carcinogenic":0,"human toxicity: carcinogenic":0},"\u03b318":{"climate change":0,"ecotoxicity: freshwater":0,"energy resources: non-renewable":0,"acidification":0,"material resources: metals\/minerals":0,"human toxicity: non-carcinogenic":0,"human toxicity: carcinogenic":0},"\u03b319":{"climate change":"3.970000e-04","ecotoxicity: freshwater":"3.950000e-04","energy resources: non-renewable":"4.010000e-04","acidification":"3.980000e-04","material resources: metals\/minerals":"4.020000e-04","human toxicity: non-carcinogenic":"3.950000e-04","human toxicity: carcinogenic":"3.980000e-04"},"\u03b320":{"climate change":0,"ecotoxicity: freshwater":0,"energy resources: non-renewable":0,"acidification":0,"material resources: metals\/minerals":0,"human toxicity: non-carcinogenic":0,"human toxicity: carcinogenic":0},"\u03b321":{"climate change":0,"ecotoxicity: freshwater":0,"energy resources: non-renewable":0,"acidification":0,"material resources: metals\/minerals":0,"human toxicity: non-carcinogenic":0,"human toxicity: carcinogenic":0},"\u03b322":{"climate change":0,"ecotoxicity: freshwater":0,"energy resources: non-renewable":0,"acidification":0,"material resources: metals\/minerals":0,"human toxicity: non-carcinogenic":0,"human toxicity: carcinogenic":0},"\u03b323":{"climate change":0,"ecotoxicity: freshwater":0,"energy resources: non-renewable":0,"acidification":0,"material resources: metals\/minerals":0,"human toxicity: non-carcinogenic":0,"human toxicity: carcinogenic":0},"\u03b324":{"climate change":"3.970000e-04","ecotoxicity: freshwater":"3.950000e-04","energy resources: non-renewable":"4.010000e-04","acidification":"3.980000e-04","material resources: metals\/minerals":"4.020000e-04","human toxicity: non-carcinogenic":"3.950000e-04","human toxicity: carcinogenic":"3.980000e-04"},"\u03b325":{"climate change":0,"ecotoxicity: freshwater":0,"energy resources: non-renewable":0,"acidification":0,"material resources: metals\/minerals":0,"human toxicity: non-carcinogenic":0,"human toxicity: carcinogenic":0},"\u03b326":{"climate change":0,"ecotoxicity: freshwater":0,"energy resources: non-renewable":0,"acidification":0,"material resources: metals\/minerals":0,"human toxicity: non-carcinogenic":0,"human toxicity: carcinogenic":0},"\u03b327":{"climate change":0,"ecotoxicity: freshwater":0,"energy resources: non-renewable":0,"acidification":0,"material resources: metals\/minerals":0,"human toxicity: non-carcinogenic":0,"human toxicity: carcinogenic":0},"\u03b328":{"climate change":0,"ecotoxicity: freshwater":0,"energy resources: non-renewable":0,"acidification":0,"material resources: metals\/minerals":0,"human toxicity: non-carcinogenic":0,"human toxicity: carcinogenic":0},"\u03b329":{"climate change":0,"ecotoxicity: freshwater":0,"energy resources: non-renewable":0,"acidification":0,"material resources: metals\/minerals":0,"human toxicity: non-carcinogenic":0,"human toxicity: carcinogenic":0}}